{
  "updated": "April 06, 2026",
  "days": {
    "April 06, 2026": [
      {
        "reward": "Coin Master Free Spins",
        "url": "https://rewards.coinmaster.com/rewards/rewards.html?c=pe_RICHDQpfOy_20260322"
      },
      {
        "reward": "Coin Master Free Spins",
        "url": "https://rewards.coinmaster.com/rewards/rewards.html?c=pe_FCB7SCoyX_20260403"
      },
      {
        "reward": "Coin Master Free Spins",
        "url": "https://rewards.coinmaster.com/rewards/rewards.html?c=pe_EMAILmnBqhI_20260330"
      },
      {
        "reward": "Coin Master Free Spins",
        "url": "https://rewards.coinmaster.com/rewards/rewards.html?c=pe_EMAILaiAqzP_20260404"
      },
      {
        "reward": "Coin Master Free Spins",
        "url": "https://rewards.coinmaster.com/rewards/rewards.html?c=pe_LINEVxoEoD_20260321"
      },
      {
        "reward": "Coin Master Free Spins",
        "url": "https://rewards.coinmaster.com/rewards/rewards.html?c=pe_EMAILNLJamu_20260401"
      }
    ],
    "April 05, 2026": [],
    "April 04, 2026": []
  }
}