{
  "updated": "March 15, 2026",
  "days": {
    "March 15, 2026": [
      {
        "reward": "Coin Master Free Spins",
        "url": "https://rewards.coinmaster.com/rewards/rewards.html?c=pe_INSkxBqXI_20260313"
      },
      {
        "reward": "Coin Master Free Spins",
        "url": "https://rewards.coinmaster.com/rewards/rewards.html?c=pe_FCBVPXCNT_20260313"
      },
      {
        "reward": "Coin Master Free Spins",
        "url": "https://rewards.coinmaster.com/rewards/rewards.html?c=pe_FCBHFfAXa_20260311"
      },
      {
        "reward": "Coin Master Free Spins",
        "url": "https://rewards.coinmaster.com/rewards/rewards.html?c=pe_RICHrdhPmp_20260223"
      },
      {
        "reward": "Coin Master free spins & coin links (March 2026) -",
        "url": "https://www.pockettactics.com/coin-master/free-spins"
      },
      {
        "reward": "Coin Master Free Spins and Coins [Daily Links Marc",
        "url": "https://coinmaster-free-spins.net/"
      },
      {
        "reward": "My Coin Master \u2014 Free Spins & Free Coins Link Toda",
        "url": "https://mycoinmaster.com/"
      },
      {
        "reward": "Coin Master \u2014 Free Spins & Free Coins Link",
        "url": "https://coinmaster-daily.com/"
      },
      {
        "reward": "Coin Master Daily Links Free Spins - 1 March 2026 ",
        "url": "https://www.reddit.com/r/Roonby/comments/1rhstr4/coin_master_daily_links_free_spins_1_march_2026/"
      },
      {
        "reward": "Coin Master Free Spin Link | Facebook",
        "url": "https://www.facebook.com/groups/petmasterspin/"
      }
    ],
    "March 14, 2026": [
      {
        "reward": "Coin Master Free Spins",
        "url": "https://coinmaster.onelink.me/2792196939?af_xp=social&pid=Reward%20link&deep_link_value=coinmaster%3A%2F%2F&deep_link_sub1=promotions&af_dp=coinmaster%3A%2F%2Fpromotions&af_force_deeplink=true&c=pe_TWIUdtWsu_20260227&af_web_dp=https%3A%2F%2Frewards.coinmaster.com%2Frewards%2Fplayonmobile.png&af_adset=TWI&af_ad="
      },
      {
        "reward": "Coin Master Free Spins",
        "url": "https://coinmaster.onelink.me/2792196939?af_xp=social&pid=Reward%20link&deep_link_value=coinmaster%3A%2F%2F&deep_link_sub1=promotions&af_dp=coinmaster%3A%2F%2Fpromotions&af_force_deeplink=true&c=pe_FCBCGWOXX_20260314&af_web_dp=https%3A%2F%2Frewards.coinmaster.com%2Frewards%2Fplayonmobile.png&af_adset=FCB&af_ad="
      },
      {
        "reward": "Coin Master Free Spins",
        "url": "https://coinmaster.onelink.me/2792196939?af_xp=social&pid=Reward%20link&deep_link_value=coinmaster%3A%2F%2F&deep_link_sub1=promotions&af_dp=coinmaster%3A%2F%2Fpromotions&af_force_deeplink=true&c=pe_INSkxBqXI_20260313&af_web_dp=https%3A%2F%2Frewards.coinmaster.com%2Frewards%2Fplayonmobile.png&af_adset=INS&af_ad="
      },
      {
        "reward": "14 March 2026 - Facebook",
        "url": "https://www.facebook.com/roonby/posts/coin-master-daily-links-free-spins-14-march-2026-coinmaster-coinmasterfreecoin-c/1435532681919747/"
      },
      {
        "reward": "Coin Master Daily Links Free Spins - 14 March 2026",
        "url": "https://www.reddit.com/r/Roonby/comments/1rtdh69/coin_master_daily_links_free_spins_14_march_2026/"
      }
    ],
    "March 13, 2026": [
      {
        "reward": "Coin Master Free Spins and Coins [Daily Links Marc",
        "url": "https://coinmaster-free-spins.net"
      },
      {
        "reward": "Coin Master 370 SPINS 03 March 2026 - Facebook",
        "url": "https://www.facebook.com/groups/reward8bp/posts/4301762830098200/"
      },
      {
        "reward": "Coin Master Daily Spins - Facebook",
        "url": "https://www.facebook.com/groups/706268672132303/posts/772371625522007/"
      }
    ]
  }
}